{
	"sn": "facebook",
	"status": 2,
	"id": "100084146149543",
	"name": "",
	"amountFriends": "68",
	"screenname": "Аня Николаева",
	"birthdate": "1990 August 17",
	"country": "",
	"isAvatarExists": false,
	"cookie": [
		{
			"domain": ".facebook.com",
			"expirationDate": 1723980752.551034,
			"hostOnly": false,
			"httpOnly": true,
			"name": "sb",
			"path": "/",
			"sameSite": "no_restriction",
			"secure": true,
			"session": false,
			"storeId": "0",
			"value": "uHT_YgciojD9hXqyZFVKD_5m"
		},
		{
			"domain": ".facebook.com",
			"expirationDate": 1723980731.034748,
			"hostOnly": false,
			"httpOnly": true,
			"name": "datr",
			"path": "/",
			"sameSite": "no_restriction",
			"secure": true,
			"session": false,
			"storeId": "0",
			"value": "uHT_YrjjevPjh3eD2ImgYvY4"
		},
		{
			"domain": ".facebook.com",
			"expirationDate": 1701178975.105575,
			"hostOnly": false,
			"httpOnly": false,
			"name": "c_user",
			"path": "/",
			"sameSite": "no_restriction",
			"secure": true,
			"session": false,
			"storeId": "0",
			"value": "100084146149543"
		},
		{
			"domain": ".facebook.com",
			"expirationDate": 1700309587.191,
			"hostOnly": false,
			"httpOnly": false,
			"name": "dpr",
			"path": "/",
			"sameSite": "no_restriction",
			"secure": true,
			"session": false,
			"storeId": "0",
			"value": "1"
		},
		{
			"domain": ".facebook.com",
			"expirationDate": 1700309587.196,
			"hostOnly": false,
			"httpOnly": false,
			"name": "cppo",
			"path": "/",
			"sameSite": "unspecified",
			"secure": true,
			"session": false,
			"storeId": "0",
			"value": "1"
		},
		{
			"domain": ".facebook.com",
			"expirationDate": 1670248011,
			"hostOnly": false,
			"httpOnly": false,
			"name": "wd",
			"path": "/",
			"sameSite": "lax",
			"secure": true,
			"session": false,
			"storeId": "0",
			"value": "1030x616"
		},
		{
			"domain": ".facebook.com",
			"hostOnly": false,
			"httpOnly": false,
			"name": "usida",
			"path": "/",
			"sameSite": "no_restriction",
			"secure": true,
			"session": true,
			"storeId": "0",
			"value": "eyJ2ZXIiOjEsImlkIjoiQXJsdWc0NjV1NW93eiIsInRpbWUiOjE2NjkyNzkyNTR9"
		},
		{
			"domain": ".facebook.com",
			"expirationDate": 1701178975.105639,
			"hostOnly": false,
			"httpOnly": true,
			"name": "xs",
			"path": "/",
			"sameSite": "no_restriction",
			"secure": true,
			"session": false,
			"storeId": "0",
			"value": "45%3AtfE0rGDTTakePA%3A2%3A1660908749%3A-1%3A6992%3A%3AAcWQrsGHGL3y8A-_CrjQV53c4FCBrSF4OvkbURHZMB8"
		},
		{
			"domain": ".facebook.com",
			"expirationDate": 1677419115.439858,
			"hostOnly": false,
			"httpOnly": true,
			"name": "fr",
			"path": "/",
			"sameSite": "no_restriction",
			"secure": true,
			"session": false,
			"storeId": "0",
			"value": "0wCOgD9RrUmYbiDM8.AWV0qpkmL_x-HZtAyfLIJ9395S8.BjhLrf.8v.AAA.0.0.BjhLts.AWUQCfG-23g"
		},
		{
			"domain": ".facebook.com",
			"hostOnly": false,
			"httpOnly": false,
			"name": "presence",
			"path": "/",
			"sameSite": "unspecified",
			"secure": true,
			"session": true,
			"storeId": "0",
			"value": "C%7B%22t3%22%3A%5B%5D%2C%22utc3%22%3A1669643216240%2C%22v%22%3A1%7D"
		}
	],
	"lastEventDate": "28.11.2022 14:33 D-05"
}