{
	"sn": "facebook",
	"custom": {},
	"lastEventDate": "25.01.2023 02:27 petr d8",
	"status": 2,
	"id": "100086609156172",
	"name": "",
	"amountFriends": "",
	"screenname": "Thelma Kim",
	"birthdate": "1998 March 16",
	"country": "Latvia",
	"isAvatarExists": false,
	"cookie": [
		{
			"domain": ".facebook.com",
			"expirationDate": 1705789281,
			"hostOnly": false,
			"httpOnly": true,
			"name": "datr",
			"path": "/",
			"sameSite": "no_restriction",
			"secure": true,
			"session": false,
			"storeId": "0",
			"value": "rqS_YwdQlR-lWlcTkL04tTKX"
		},
		{
			"domain": ".facebook.com",
			"expirationDate": 1705789281,
			"hostOnly": false,
			"httpOnly": true,
			"name": "sb",
			"path": "/",
			"sameSite": "no_restriction",
			"secure": true,
			"session": false,
			"storeId": "0",
			"value": "sqS_Y3BHGNMcXZANSGcsgt70"
		},
		{
			"domain": ".facebook.com",
			"expirationDate": 1706149149.114608,
			"hostOnly": false,
			"httpOnly": false,
			"name": "c_user",
			"path": "/",
			"sameSite": "no_restriction",
			"secure": true,
			"session": false,
			"storeId": "0",
			"value": "100086609156172"
		},
		{
			"domain": ".facebook.com",
			"expirationDate": 1705789281,
			"hostOnly": false,
			"httpOnly": true,
			"name": "oo",
			"path": "/",
			"sameSite": "no_restriction",
			"secure": true,
			"session": false,
			"storeId": "0",
			"value": "v1"
		},
		{
			"domain": ".facebook.com",
			"expirationDate": 1675217754,
			"hostOnly": false,
			"httpOnly": false,
			"name": "dpr",
			"path": "/",
			"sameSite": "no_restriction",
			"secure": true,
			"session": false,
			"storeId": "0",
			"value": "1"
		},
		{
			"domain": ".facebook.com",
			"expirationDate": 1675218169,
			"hostOnly": false,
			"httpOnly": false,
			"name": "wd",
			"path": "/",
			"sameSite": "lax",
			"secure": true,
			"session": false,
			"storeId": "0",
			"value": "1036x684"
		},
		{
			"domain": ".facebook.com",
			"expirationDate": 1706149149.114658,
			"hostOnly": false,
			"httpOnly": true,
			"name": "xs",
			"path": "/",
			"sameSite": "no_restriction",
			"secure": true,
			"session": false,
			"storeId": "0",
			"value": "27%3AxbELKC_93lRAuQ%3A2%3A1673503962%3A-1%3A-1%3A%3AAcX_jPxufMh2v8Ld8o_z0DP9ZasEYWgASyhfa5jURyo"
		},
		{
			"domain": ".facebook.com",
			"expirationDate": 1682389202.808865,
			"hostOnly": false,
			"httpOnly": true,
			"name": "fr",
			"path": "/",
			"sameSite": "no_restriction",
			"secure": true,
			"session": false,
			"storeId": "0",
			"value": "0OUrQpj5bLaxGLgkm.AWWmtfFLEJZ1k23N7vC3ayf5p3I.Bj0JGd.PM.AAA.0.0.Bj0JHT.AWXBICTdlC0"
		},
		{
			"domain": ".facebook.com",
			"hostOnly": false,
			"httpOnly": false,
			"name": "presence",
			"path": "/",
			"sameSite": "unspecified",
			"secure": true,
			"session": true,
			"storeId": "0",
			"value": "C%7B%22t3%22%3A%5B%5D%2C%22utc3%22%3A1674613344551%2C%22v%22%3A1%7D"
		}
	]
}