{
	"sn": "facebook",
	"status": 2,
	"id": "100088119227784",
	"name": "",
	"amountFriends": "",
	"screenname": "Настёна Попова",
	"birthdate": "1998 November 29",
	"country": "",
	"isAvatarExists": false,
	"cookie": [
		{
			"domain": ".facebook.com",
			"expirationDate": 1704702502.927153,
			"hostOnly": false,
			"httpOnly": true,
			"name": "sb",
			"path": "/",
			"sameSite": "no_restriction",
			"secure": true,
			"session": false,
			"storeId": "0",
			"value": "K-KIY7qksCByYTtbl-4F0m9c"
		},
		{
			"domain": ".facebook.com",
			"expirationDate": 1704702502.927258,
			"hostOnly": false,
			"httpOnly": true,
			"name": "datr",
			"path": "/",
			"sameSite": "no_restriction",
			"secure": true,
			"session": false,
			"storeId": "0",
			"value": "K-KIY8u00Mpy2u914G7NW-k4"
		},
		{
			"domain": ".facebook.com",
			"expirationDate": 1701678538.394124,
			"hostOnly": false,
			"httpOnly": false,
			"name": "c_user",
			"path": "/",
			"sameSite": "no_restriction",
			"secure": true,
			"session": false,
			"storeId": "0",
			"value": "100088119227784"
		},
		{
			"domain": ".facebook.com",
			"expirationDate": 1670747667,
			"hostOnly": false,
			"httpOnly": false,
			"name": "dpr",
			"path": "/",
			"sameSite": "no_restriction",
			"secure": true,
			"session": false,
			"storeId": "0",
			"value": "1.25"
		},
		{
			"domain": ".facebook.com",
			"expirationDate": 1670747669,
			"hostOnly": false,
			"httpOnly": false,
			"name": "wd",
			"path": "/",
			"sameSite": "lax",
			"secure": true,
			"session": false,
			"storeId": "0",
			"value": "1036x686"
		},
		{
			"domain": ".facebook.com",
			"expirationDate": 1701678538.394155,
			"hostOnly": false,
			"httpOnly": true,
			"name": "xs",
			"path": "/",
			"sameSite": "no_restriction",
			"secure": true,
			"session": false,
			"storeId": "0",
			"value": "31%3Ap6x7mSSkO5RdMQ%3A2%3A1669915223%3A-1%3A-1%3A%3AAcWNwoD3cxp9FoLbWGoQERW9ARsATimFGYoYb88DRw"
		},
		{
			"domain": ".facebook.com",
			"expirationDate": 1677918592.597529,
			"hostOnly": false,
			"httpOnly": true,
			"name": "fr",
			"path": "/",
			"sameSite": "no_restriction",
			"secure": true,
			"session": false,
			"storeId": "0",
			"value": "0rLRJdaubjCfD7PAL.AWVLc1O0dk2AHKavIiDAPwAiAbg.BjjFpL.sC.AAA.0.0.BjjFqB.AWU7sUPcSfM"
		},
		{
			"domain": ".facebook.com",
			"hostOnly": false,
			"httpOnly": false,
			"name": "presence",
			"path": "/",
			"sameSite": "unspecified",
			"secure": true,
			"session": true,
			"storeId": "0",
			"value": "C%7B%22t3%22%3A%5B%5D%2C%22utc3%22%3A1670142811500%2C%22v%22%3A1%7D"
		}
	],
	"lastEventDate": "04.12.2022 08:34 заполняем профиль LT"
}