{
	"sn": "facebook",
	"custom": {},
	"lastEventDate": "06.02.2023 23:27 petr d15",
	"status": 2,
	"id": "100087203140474",
	"name": "",
	"amountFriends": "",
	"screenname": "Laurie Gibson",
	"birthdate": "1999 October 19",
	"country": "Latvia",
	"isAvatarExists": false,
	"cookie": [
		{
			"domain": ".facebook.com",
			"expirationDate": 1705763845,
			"hostOnly": false,
			"httpOnly": true,
			"name": "datr",
			"path": "/",
			"sameSite": "no_restriction",
			"secure": true,
			"session": false,
			"storeId": "0",
			"value": "Ys--Y7n_xJNUj_yED6Lw4k8q"
		},
		{
			"domain": ".facebook.com",
			"expirationDate": 1705763845,
			"hostOnly": false,
			"httpOnly": true,
			"name": "sb",
			"path": "/",
			"sameSite": "no_restriction",
			"secure": true,
			"session": false,
			"storeId": "0",
			"value": "Zc--Yy0c2GegHXRZTqQS0MuE"
		},
		{
			"domain": ".facebook.com",
			"expirationDate": 1705763845,
			"hostOnly": false,
			"httpOnly": false,
			"name": "locale",
			"path": "/",
			"sameSite": "no_restriction",
			"secure": true,
			"session": false,
			"storeId": "0",
			"value": "en_US"
		},
		{
			"domain": ".facebook.com",
			"expirationDate": 1707261810.252571,
			"hostOnly": false,
			"httpOnly": false,
			"name": "c_user",
			"path": "/",
			"sameSite": "no_restriction",
			"secure": true,
			"session": false,
			"storeId": "0",
			"value": "100087203140474"
		},
		{
			"domain": ".facebook.com",
			"expirationDate": 1676330714,
			"hostOnly": false,
			"httpOnly": false,
			"name": "dpr",
			"path": "/",
			"sameSite": "no_restriction",
			"secure": true,
			"session": false,
			"storeId": "0",
			"value": "1.25"
		},
		{
			"domain": ".facebook.com",
			"expirationDate": 1676330714,
			"hostOnly": false,
			"httpOnly": false,
			"name": "wd",
			"path": "/",
			"sameSite": "lax",
			"secure": true,
			"session": false,
			"storeId": "0",
			"value": "1302x763"
		},
		{
			"domain": ".facebook.com",
			"expirationDate": 1707261810.252608,
			"hostOnly": false,
			"httpOnly": true,
			"name": "xs",
			"path": "/",
			"sameSite": "no_restriction",
			"secure": true,
			"session": false,
			"storeId": "0",
			"value": "8%3AFMNJpdd79qxqyQ%3A2%3A1673789920%3A-1%3A-1%3A%3AAcVKv8AELAjtolibkgz63yMqIcXsOBcMWpiu09ooSLY"
		},
		{
			"domain": ".facebook.com",
			"expirationDate": 1683501808.252627,
			"hostOnly": false,
			"httpOnly": true,
			"name": "fr",
			"path": "/",
			"sameSite": "no_restriction",
			"secure": true,
			"session": false,
			"storeId": "0",
			"value": "063Kuub1kSEGffFro.AWVw4Ti7ccVUymyVY6tVvQGYRvo.Bj4Yvz.FB.AAA.0.0.Bj4Yvz.AWVbNmbgNS0"
		},
		{
			"domain": ".facebook.com",
			"hostOnly": false,
			"httpOnly": false,
			"name": "presence",
			"path": "/",
			"sameSite": "unspecified",
			"secure": true,
			"session": true,
			"storeId": "0",
			"value": "C%7B%22t3%22%3A%5B%5D%2C%22utc3%22%3A1675725891769%2C%22v%22%3A1%7D"
		}
	]
}