{
	"sn": "facebook",
	"custom": {},
	"status": 2,
	"id": "100088336128355",
	"name": "",
	"amountFriends": "207",
	"screenname": "Saniyat Vikulina",
	"birthdate": "2000 March 7",
	"country": "Latvia",
	"isAvatarExists": false,
	"cookie": [
		{
			"domain": ".facebook.com",
			"expirationDate": 1705133029.775823,
			"hostOnly": false,
			"httpOnly": true,
			"name": "datr",
			"path": "/",
			"sameSite": "no_restriction",
			"secure": true,
			"session": false,
			"storeId": "0",
			"value": "4OuSY7BHUPVkDqwQB_05H58D"
		},
		{
			"domain": ".facebook.com",
			"expirationDate": 1705133064.476277,
			"hostOnly": false,
			"httpOnly": true,
			"name": "sb",
			"path": "/",
			"sameSite": "no_restriction",
			"secure": true,
			"session": false,
			"storeId": "0",
			"value": "5euSY-eGMYr2LCRAEEwtptaC"
		},
		{
			"domain": ".facebook.com",
			"expirationDate": 1705920657.080583,
			"hostOnly": false,
			"httpOnly": false,
			"name": "c_user",
			"path": "/",
			"sameSite": "no_restriction",
			"secure": true,
			"session": false,
			"storeId": "0",
			"value": "100088336128355"
		},
		{
			"domain": ".facebook.com",
			"expirationDate": 1674989706,
			"hostOnly": false,
			"httpOnly": false,
			"name": "wd",
			"path": "/",
			"sameSite": "lax",
			"secure": true,
			"session": false,
			"storeId": "0",
			"value": "1034x620"
		},
		{
			"domain": ".facebook.com",
			"hostOnly": false,
			"httpOnly": false,
			"name": "usida",
			"path": "/",
			"sameSite": "no_restriction",
			"secure": true,
			"session": true,
			"storeId": "0",
			"value": "eyJ2ZXIiOjEsImlkIjoiQXJvb3E3eWRtMTBhZiIsInRpbWUiOjE2NzQwNTEyNjJ9"
		},
		{
			"domain": ".facebook.com",
			"expirationDate": 1705920657.080627,
			"hostOnly": false,
			"httpOnly": true,
			"name": "xs",
			"path": "/",
			"sameSite": "no_restriction",
			"secure": true,
			"session": false,
			"storeId": "0",
			"value": "48%3AE-eiyOHFFbbSqQ%3A2%3A1670573061%3A-1%3A5599%3A%3AAcV4DVoGUvs68L8hFIljSQKSxIu-y1y3dUUA7624FUc"
		},
		{
			"domain": ".facebook.com",
			"expirationDate": 1682160791.926021,
			"hostOnly": false,
			"httpOnly": true,
			"name": "fr",
			"path": "/",
			"sameSite": "no_restriction",
			"secure": true,
			"session": false,
			"storeId": "0",
			"value": "0t57lA1LoTu1shQ0l.AWXceC2KfZioa-ak6GHGvROQZzs.BjzRUQ.46.AAA.0.0.BjzRWY.AWW-D_7qnbE"
		},
		{
			"domain": ".facebook.com",
			"hostOnly": false,
			"httpOnly": false,
			"name": "presence",
			"path": "/",
			"sameSite": "unspecified",
			"secure": true,
			"session": true,
			"storeId": "0",
			"value": "C%7B%22lm3%22%3A%22g.5695664310553337%22%2C%22t3%22%3A%5B%5D%2C%22utc3%22%3A1674384902133%2C%22v%22%3A1%7D"
		}
	],
	"lastEventDate": "22.01.2023 11:19 D-05"
}