{
	"sn": "facebook",
	"login": "37125259021",
	"password": "aTa333nmv",
	"status": 2,
	"id": "100088504484631",
	"name": "",
	"amountFriends": "",
	"screenname": "Ludmila Lace",
	"birthdate": "1997 July 22",
	"country": "Daugavpils",
	"isAvatarExists": false,
	"cookie": [
		{
			"domain": ".facebook.com",
			"expirationDate": 1705254125.32636,
			"hostOnly": false,
			"httpOnly": true,
			"name": "datr",
			"path": "/",
			"sameSite": "no_restriction",
			"secure": true,
			"session": false,
			"storeId": "0",
			"value": "6cSUY68g2Qx-XIaHj_g83kdB"
		},
		{
			"domain": ".facebook.com",
			"expirationDate": 1705254193.357943,
			"hostOnly": false,
			"httpOnly": true,
			"name": "sb",
			"path": "/",
			"sameSite": "no_restriction",
			"secure": true,
			"session": false,
			"storeId": "0",
			"value": "7MSUY1Ow_7Es2QuqIsIf5b2J"
		},
		{
			"domain": ".facebook.com",
			"expirationDate": 1671298993.357757,
			"hostOnly": false,
			"httpOnly": false,
			"name": "locale",
			"path": "/",
			"sameSite": "no_restriction",
			"secure": true,
			"session": false,
			"storeId": "0",
			"value": "en_US"
		},
		{
			"domain": ".facebook.com",
			"expirationDate": 1702809249.585539,
			"hostOnly": false,
			"httpOnly": false,
			"name": "c_user",
			"path": "/",
			"sameSite": "no_restriction",
			"secure": true,
			"session": false,
			"storeId": "0",
			"value": "100088504484631"
		},
		{
			"domain": ".facebook.com",
			"expirationDate": 1671878063,
			"hostOnly": false,
			"httpOnly": false,
			"name": "dpr",
			"path": "/",
			"sameSite": "no_restriction",
			"secure": true,
			"session": false,
			"storeId": "0",
			"value": "1"
		},
		{
			"domain": ".facebook.com",
			"expirationDate": 1702809249.585591,
			"hostOnly": false,
			"httpOnly": true,
			"name": "xs",
			"path": "/",
			"sameSite": "no_restriction",
			"secure": true,
			"session": false,
			"storeId": "0",
			"value": "26%3AA3ibXElcEJ558w%3A2%3A1670694192%3A-1%3A-1%3A%3AAcUWIlYwLrZ07DD7aW1ehpgVGdRcfNl572h_wcGyug"
		},
		{
			"domain": ".facebook.com",
			"expirationDate": 1671878220,
			"hostOnly": false,
			"httpOnly": false,
			"name": "wd",
			"path": "/",
			"sameSite": "lax",
			"secure": true,
			"session": false,
			"storeId": "0",
			"value": "1036x684"
		},
		{
			"domain": ".facebook.com",
			"expirationDate": 1679049265.628809,
			"hostOnly": false,
			"httpOnly": true,
			"name": "fr",
			"path": "/",
			"sameSite": "no_restriction",
			"secure": true,
			"session": false,
			"storeId": "0",
			"value": "08pjFOapu5xbOd9WZ.AWUeuA-tICPiX609pW3c44NrE6c.BjnZsi.NU.AAA.0.0.BjnZsy.AWXh4cNp904"
		},
		{
			"domain": ".facebook.com",
			"hostOnly": false,
			"httpOnly": false,
			"name": "presence",
			"path": "/",
			"sameSite": "unspecified",
			"secure": true,
			"session": true,
			"storeId": "0",
			"value": "C%7B%22t3%22%3A%5B%5D%2C%22utc3%22%3A1671273397027%2C%22v%22%3A1%7D"
		}
	],
	"lastEventDate": "17.12.2022 10:47 petr d4",
	"email": "dmisuaburov@outlook.com",
	"emailPassword": "f6nT111rlz4",
	"imapHost": "outlook.office365.com",
	"imapPort": "993"
}