{
	"sn": "facebook",
	"custom": {},
	"status": 2,
	"id": "100088593126331",
	"name": "",
	"amountFriends": "223",
	"screenname": "Zhenya Galich",
	"birthdate": "1999 February 1",
	"country": "Latvia",
	"isAvatarExists": false,
	"cookie": [
		{
			"domain": ".facebook.com",
			"expirationDate": 1705133340.256225,
			"hostOnly": false,
			"httpOnly": true,
			"name": "datr",
			"path": "/",
			"sameSite": "no_restriction",
			"secure": true,
			"session": false,
			"storeId": "0",
			"value": "F-2SYyadg4xwscCzMee0z9Yp"
		},
		{
			"domain": ".facebook.com",
			"expirationDate": 1705133387.792227,
			"hostOnly": false,
			"httpOnly": true,
			"name": "sb",
			"path": "/",
			"sameSite": "no_restriction",
			"secure": true,
			"session": false,
			"storeId": "0",
			"value": "G-2SY_G2sVLAJOmNcMoDhDXX"
		},
		{
			"domain": ".facebook.com",
			"expirationDate": 1705137565.782769,
			"hostOnly": false,
			"httpOnly": false,
			"name": "c_user",
			"path": "/",
			"sameSite": "no_restriction",
			"secure": true,
			"session": false,
			"storeId": "0",
			"value": "100088593126331"
		},
		{
			"domain": ".facebook.com",
			"expirationDate": 1705137558.849,
			"hostOnly": false,
			"httpOnly": false,
			"name": "usida",
			"path": "/",
			"sameSite": "no_restriction",
			"secure": true,
			"session": false,
			"storeId": "0",
			"value": "eyJ2ZXIiOjEsImlkIjoiQXJubWVuajFiN2RjZ3AiLCJ0aW1lIjoxNjcyMjYzMzQzfQ%3D%3D"
		},
		{
			"domain": ".facebook.com",
			"expirationDate": 1674206465,
			"hostOnly": false,
			"httpOnly": false,
			"name": "wd",
			"path": "/",
			"sameSite": "lax",
			"secure": true,
			"session": false,
			"storeId": "0",
			"value": "1034x620"
		},
		{
			"domain": ".facebook.com",
			"expirationDate": 1705137565.782814,
			"hostOnly": false,
			"httpOnly": true,
			"name": "xs",
			"path": "/",
			"sameSite": "no_restriction",
			"secure": true,
			"session": false,
			"storeId": "0",
			"value": "12%3AzJrLWpniIM9YUg%3A2%3A1670573385%3A-1%3A5599%3A%3AAcWdImzICblEjaDhLDeSw22EOk-iu8aczr4gPAsd3dY"
		},
		{
			"domain": ".facebook.com",
			"expirationDate": 1681377569.29484,
			"hostOnly": false,
			"httpOnly": true,
			"name": "fr",
			"path": "/",
			"sameSite": "no_restriction",
			"secure": true,
			"session": false,
			"storeId": "0",
			"value": "0Gf0eDd3hVjL63cKW.AWVX2uSnbnnVivHPBMcFrFLD-_A.BjwSIe.yT.AAA.0.0.BjwSIi.AWVzZySlMv8"
		},
		{
			"domain": ".facebook.com",
			"hostOnly": false,
			"httpOnly": false,
			"name": "presence",
			"path": "/",
			"sameSite": "unspecified",
			"secure": true,
			"session": true,
			"storeId": "0",
			"value": "C%7B%22lm3%22%3A%22u.100053340452824%22%2C%22t3%22%3A%5B%7B%22i%22%3A%22u.1570410359%22%7D%2C%7B%22i%22%3A%22u.100058521288100%22%7D%5D%2C%22utc3%22%3A1673601661579%2C%22v%22%3A1%7D"
		}
	],
	"lastEventDate": "13.01.2023 09:21 D-01"
}