{
	"sn": "facebook",
	"login": "Roberson19951@outlook.com",
	"password": "mQSl_f7h",
	"status": 2,
	"id": "100086907073509",
	"custom": {},
	"lastEventDate": "19.01.2023 13:30 petr d4",
	"name": "",
	"amountFriends": "",
	"screenname": "Betty Roberson",
	"birthdate": "1995 April 19",
	"country": "Latvia",
	"isAvatarExists": false,
	"cookie": [
		{
			"domain": ".facebook.com",
			"expirationDate": 1708243799.184746,
			"hostOnly": false,
			"httpOnly": true,
			"name": "datr",
			"path": "/",
			"sameSite": "no_restriction",
			"secure": true,
			"session": false,
			"storeId": "0",
			"value": "U2PCY2-q2FQ9OL5iKibqAXE_"
		},
		{
			"domain": ".facebook.com",
			"expirationDate": 1708243849.757161,
			"hostOnly": false,
			"httpOnly": true,
			"name": "sb",
			"path": "/",
			"sameSite": "no_restriction",
			"secure": true,
			"session": false,
			"storeId": "0",
			"value": "VmPCY9oEFvU-Yki3fl4ZiRQt"
		},
		{
			"domain": ".facebook.com",
			"expirationDate": 1705670879.033247,
			"hostOnly": false,
			"httpOnly": false,
			"name": "c_user",
			"path": "/",
			"sameSite": "no_restriction",
			"secure": true,
			"session": false,
			"storeId": "0",
			"value": "100086907073509"
		},
		{
			"domain": ".facebook.com",
			"expirationDate": 1674739835,
			"hostOnly": false,
			"httpOnly": false,
			"name": "dpr",
			"path": "/",
			"sameSite": "no_restriction",
			"secure": true,
			"session": false,
			"storeId": "0",
			"value": "1.25"
		},
		{
			"domain": ".facebook.com",
			"expirationDate": 1674739835,
			"hostOnly": false,
			"httpOnly": false,
			"name": "wd",
			"path": "/",
			"sameSite": "lax",
			"secure": true,
			"session": false,
			"storeId": "0",
			"value": "1038x686"
		},
		{
			"domain": ".facebook.com",
			"expirationDate": 1705670879.033281,
			"hostOnly": false,
			"httpOnly": true,
			"name": "xs",
			"path": "/",
			"sameSite": "no_restriction",
			"secure": true,
			"session": false,
			"storeId": "0",
			"value": "46%3AkEDi12DIGWr7Xw%3A2%3A1673683845%3A-1%3A14804%3A%3AAcVA77353TVblGPtmj1OSfMxEes28KEPV6W5fXFabw"
		},
		{
			"domain": ".facebook.com",
			"expirationDate": 1681910900.413296,
			"hostOnly": false,
			"httpOnly": true,
			"name": "fr",
			"path": "/",
			"sameSite": "no_restriction",
			"secure": true,
			"session": false,
			"storeId": "0",
			"value": "0EWEFMJcXYwvGEERv.AWUHSUvP2KLLr0Vj2KvTaKLX8I8.BjyUVf.QQ.AAA.0.0.BjyUV1.AWX-EIXZZvM"
		},
		{
			"domain": ".facebook.com",
			"hostOnly": false,
			"httpOnly": false,
			"name": "presence",
			"path": "/",
			"sameSite": "unspecified",
			"secure": true,
			"session": true,
			"storeId": "0",
			"value": "C%7B%22t3%22%3A%5B%5D%2C%22utc3%22%3A1674135012495%2C%22v%22%3A1%7D"
		}
	]
}