{
	"sn": "facebook",
	"custom": {},
	"lastEventDate": "11.12.2022 10:52 testotvyaz",
	"status": 2,
	"id": "100088437527454",
	"name": "",
	"amountFriends": "",
	"screenname": "Ārija Sokolows",
	"birthdate": "2003 October 15",
	"country": "",
	"isAvatarExists": false,
	"cookie": [
		{
			"domain": ".facebook.com",
			"expirationDate": 1671360738,
			"hostOnly": false,
			"httpOnly": false,
			"name": "dpr",
			"path": "/",
			"sameSite": "no_restriction",
			"secure": true,
			"session": false,
			"storeId": "0",
			"value": "1.25"
		},
		{
			"domain": ".facebook.com",
			"expirationDate": 1705251108.8649,
			"hostOnly": false,
			"httpOnly": true,
			"name": "datr",
			"path": "/",
			"sameSite": "no_restriction",
			"secure": true,
			"session": false,
			"storeId": "0",
			"value": "ILmUY-4jRAW2m1WY-3u5Q3em"
		},
		{
			"domain": ".facebook.com",
			"expirationDate": 1705251178.192156,
			"hostOnly": false,
			"httpOnly": true,
			"name": "sb",
			"path": "/",
			"sameSite": "no_restriction",
			"secure": true,
			"session": false,
			"storeId": "0",
			"value": "JLmUY7_o14FhcWNhv7oVFRdd"
		},
		{
			"domain": ".facebook.com",
			"expirationDate": 1671295978.191952,
			"hostOnly": false,
			"httpOnly": false,
			"name": "locale",
			"path": "/",
			"sameSite": "no_restriction",
			"secure": true,
			"session": false,
			"storeId": "0",
			"value": "lv_LV"
		},
		{
			"domain": ".facebook.com",
			"expirationDate": 1702290579.878244,
			"hostOnly": false,
			"httpOnly": false,
			"name": "c_user",
			"path": "/",
			"sameSite": "no_restriction",
			"secure": true,
			"session": false,
			"storeId": "0",
			"value": "100088437527454"
		},
		{
			"domain": ".facebook.com",
			"expirationDate": 1702290579.878274,
			"hostOnly": false,
			"httpOnly": true,
			"name": "xs",
			"path": "/",
			"sameSite": "no_restriction",
			"secure": true,
			"session": false,
			"storeId": "0",
			"value": "24%3AbW1jb53bnJCeNQ%3A2%3A1670691176%3A-1%3A-1%3A%3AAcX7bkl_pAGFH-5Yem0CRMy_xumNHp4spSPyWivdLw"
		},
		{
			"domain": ".facebook.com",
			"expirationDate": 1671360738,
			"hostOnly": false,
			"httpOnly": false,
			"name": "wd",
			"path": "/",
			"sameSite": "lax",
			"secure": true,
			"session": false,
			"storeId": "0",
			"value": "1040x687"
		},
		{
			"domain": ".facebook.com",
			"expirationDate": 1678531753.980821,
			"hostOnly": false,
			"httpOnly": true,
			"name": "fr",
			"path": "/",
			"sameSite": "no_restriction",
			"secure": true,
			"session": false,
			"storeId": "0",
			"value": "0EtX0G6S1UFr4PrAU.AWVYCsLdZPZ2DbybA-FLOTFRAiQ.BjlbQ1.C1.AAA.0.0.BjlbWq.AWXwg7PycCU"
		},
		{
			"domain": ".facebook.com",
			"hostOnly": false,
			"httpOnly": false,
			"name": "presence",
			"path": "/",
			"sameSite": "unspecified",
			"secure": true,
			"session": true,
			"storeId": "0",
			"value": "C%7B%22t3%22%3A%5B%5D%2C%22utc3%22%3A1670755895408%2C%22v%22%3A1%7D"
		}
	]
}