{
	"sn": "facebook",
	"custom": {},
	"lastEventDate": "13.02.2023 17:20 petr d37",
	"status": 2,
	"id": "100088767736625",
	"name": "",
	"amountFriends": "",
	"screenname": "Inita Rose",
	"birthdate": "2001 November 1",
	"country": "Latvia",
	"isAvatarExists": false,
	"cookie": [
		{
			"domain": ".facebook.com",
			"expirationDate": 1707492827,
			"hostOnly": false,
			"httpOnly": true,
			"name": "datr",
			"path": "/",
			"sameSite": "no_restriction",
			"secure": true,
			"session": false,
			"storeId": "0",
			"value": "R5fPY2BSt0cJUaWUiBrAmqmW"
		},
		{
			"domain": ".facebook.com",
			"expirationDate": 1707492827,
			"hostOnly": false,
			"httpOnly": true,
			"name": "sb",
			"path": "/",
			"sameSite": "no_restriction",
			"secure": true,
			"session": false,
			"storeId": "0",
			"value": "S5fPY8jUgRaq9amJzwm12nlo"
		},
		{
			"domain": ".facebook.com",
			"expirationDate": 1707753671.080228,
			"hostOnly": false,
			"httpOnly": false,
			"name": "c_user",
			"path": "/",
			"sameSite": "no_restriction",
			"secure": true,
			"session": false,
			"storeId": "0",
			"value": "100088767736625"
		},
		{
			"domain": ".facebook.com",
			"expirationDate": 1676822570,
			"hostOnly": false,
			"httpOnly": false,
			"name": "dpr",
			"path": "/",
			"sameSite": "no_restriction",
			"secure": true,
			"session": false,
			"storeId": "0",
			"value": "1.25"
		},
		{
			"domain": ".facebook.com",
			"expirationDate": 1676822570,
			"hostOnly": false,
			"httpOnly": false,
			"name": "wd",
			"path": "/",
			"sameSite": "lax",
			"secure": true,
			"session": false,
			"storeId": "0",
			"value": "1038x686"
		},
		{
			"domain": ".facebook.com",
			"expirationDate": 1707753671.080299,
			"hostOnly": false,
			"httpOnly": true,
			"name": "xs",
			"path": "/",
			"sameSite": "no_restriction",
			"secure": true,
			"session": false,
			"storeId": "0",
			"value": "45%3ABBy8-0TREFdGBA%3A2%3A1674549125%3A-1%3A11287%3A%3AAcV5Msnuc7BU5Kl86N7CHm3gymnorr5sEoNl52CQm_c"
		},
		{
			"domain": ".facebook.com",
			"expirationDate": 1683993670.08034,
			"hostOnly": false,
			"httpOnly": true,
			"name": "fr",
			"path": "/",
			"sameSite": "no_restriction",
			"secure": true,
			"session": false,
			"storeId": "0",
			"value": "0WwiGE0ILaYrXVF8R.AWXS7YXkk2T8pkpyLFV9sBmmZms.Bj6Q1H.NN.AAA.0.0.Bj6Q1H.AWUEFpYsGaw"
		},
		{
			"domain": ".facebook.com",
			"hostOnly": false,
			"httpOnly": false,
			"name": "presence",
			"path": "/",
			"sameSite": "unspecified",
			"secure": true,
			"session": true,
			"storeId": "0",
			"value": "C%7B%22t3%22%3A%5B%5D%2C%22utc3%22%3A1676217747417%2C%22v%22%3A1%7D"
		}
	]
}