{
	"sn": "facebook",
	"lastEventDate": "28.12.2022 18:03 D-14(mini) LV_1",
	"status": 2,
	"id": "100084739434855",
	"name": "",
	"amountFriends": "86",
	"screenname": "Ксения Лучшева",
	"birthdate": "1983 September 5",
	"country": "",
	"isAvatarExists": false,
	"cookie": [
		{
			"domain": ".facebook.com",
			"expirationDate": 1724852160,
			"hostOnly": false,
			"httpOnly": true,
			"name": "dbln",
			"path": "/login/device-based/",
			"sameSite": "unspecified",
			"secure": true,
			"session": false,
			"storeId": "0",
			"value": "%7B%22100084739434855%22%3A%22jGVodxn8%22%7D"
		},
		{
			"domain": ".facebook.com",
			"expirationDate": 1724852147,
			"hostOnly": false,
			"httpOnly": true,
			"name": "datr",
			"path": "/",
			"sameSite": "unspecified",
			"secure": true,
			"session": false,
			"storeId": "0",
			"value": "s8AMY8l9-JsiVwaR_zdzQjmp"
		},
		{
			"domain": ".facebook.com",
			"expirationDate": 1734526513.430682,
			"hostOnly": false,
			"httpOnly": true,
			"name": "sb",
			"path": "/",
			"sameSite": "no_restriction",
			"secure": true,
			"session": false,
			"storeId": "0",
			"value": "s8AMYzgHYGReWDHhT2wZRtIX"
		},
		{
			"domain": ".facebook.com",
			"expirationDate": 1703783742.980868,
			"hostOnly": false,
			"httpOnly": false,
			"name": "c_user",
			"path": "/",
			"sameSite": "no_restriction",
			"secure": true,
			"session": false,
			"storeId": "0",
			"value": "100084739434855"
		},
		{
			"domain": ".facebook.com",
			"expirationDate": 1672852596,
			"hostOnly": false,
			"httpOnly": false,
			"name": "wd",
			"path": "/",
			"sameSite": "lax",
			"secure": true,
			"session": false,
			"storeId": "0",
			"value": "1032x618"
		},
		{
			"domain": ".facebook.com",
			"hostOnly": false,
			"httpOnly": false,
			"name": "usida",
			"path": "/",
			"sameSite": "no_restriction",
			"secure": true,
			"session": true,
			"storeId": "0",
			"value": "eyJ2ZXIiOjEsImlkIjoiQXJuaG5tOTFwaGQydDUiLCJ0aW1lIjoxNjcyMDQyMjYyfQ%3D%3D"
		},
		{
			"domain": ".facebook.com",
			"expirationDate": 1703783742.980908,
			"hostOnly": false,
			"httpOnly": true,
			"name": "xs",
			"path": "/",
			"sameSite": "no_restriction",
			"secure": true,
			"session": false,
			"storeId": "0",
			"value": "42%3AowzINRsnuApIBA%3A2%3A1671454510%3A-1%3A8960%3A%3AAcVlyvm6pAUk-rTPruH_cIYO7iMKXIiJatOqozunUA"
		},
		{
			"domain": ".facebook.com",
			"expirationDate": 1680023741.980928,
			"hostOnly": false,
			"httpOnly": true,
			"name": "fr",
			"path": "/",
			"sameSite": "no_restriction",
			"secure": true,
			"session": false,
			"storeId": "0",
			"value": "0blT61hBSJJ6ianFJ.AWXgMoA5HJ9J6QaXFdaVpVdbUd8.BjrHm_.gM.AAA.0.0.BjrHm_.AWXIFmr7NP0"
		},
		{
			"domain": ".facebook.com",
			"hostOnly": false,
			"httpOnly": false,
			"name": "presence",
			"path": "/",
			"sameSite": "unspecified",
			"secure": true,
			"session": true,
			"storeId": "0",
			"value": "C%7B%22t3%22%3A%5B%5D%2C%22utc3%22%3A1672247771896%2C%22v%22%3A1%7D"
		}
	],
	"funPages": [
		"https://www.facebook.com/profile.php?id=100088441130721",
		"https://www.facebook.com/profile.php?id=100088412602688"
	],
	"adsToken": "EAABsbCS1iHgBAO4WiXa22wC6XWyVH5h2KkZBj1ggHuznJO5roqyzihnExYozd1zMZCMpS9O27Ykzo70uCwD9ZCObYcZBKPZAkVHfWtxf0zPuhDaumS8YvOS0Bc5PmlkU470BYcphDHIKMbHjw8qmLgRj6oZAPA7fCGRL6PeEKei2bRDv8wv2tLGr7hZBIpE94MZD"
}