{
	"sn": "facebook",
	"login": "996995123024",
	"password": "qwe123rtY",
	"status": 2,
	"id": "100089148694729",
	"custom": {},
	"name": "",
	"amountFriends": "",
	"cookie": [
		{
			"domain": ".facebook.com",
			"expirationDate": 1706620419.683747,
			"hostOnly": false,
			"httpOnly": true,
			"name": "dbln",
			"path": "/login/device-based/",
			"sameSite": "no_restriction",
			"secure": true,
			"session": false,
			"storeId": "0",
			"value": "%7B%22100089148694729%22%3A%22FST38WbH%22%7D"
		},
		{
			"domain": ".facebook.com",
			"expirationDate": 1706620366.990424,
			"hostOnly": false,
			"httpOnly": true,
			"name": "sb",
			"path": "/",
			"sameSite": "no_restriction",
			"secure": true,
			"session": false,
			"storeId": "0",
			"value": "n52pYwxW0EaPWDIvIxXsoQo9"
		},
		{
			"domain": ".facebook.com",
			"expirationDate": 1706620324.239314,
			"hostOnly": false,
			"httpOnly": true,
			"name": "datr",
			"path": "/",
			"sameSite": "no_restriction",
			"secure": true,
			"session": false,
			"storeId": "0",
			"value": "n52pY2Z55Y8P9C9z5fFnEeH4"
		},
		{
			"domain": ".facebook.com",
			"expirationDate": 1705671507.604715,
			"hostOnly": false,
			"httpOnly": false,
			"name": "c_user",
			"path": "/",
			"sameSite": "no_restriction",
			"secure": true,
			"session": false,
			"storeId": "0",
			"value": "100089148694729"
		},
		{
			"domain": ".facebook.com",
			"expirationDate": 1674740989,
			"hostOnly": false,
			"httpOnly": false,
			"name": "dpr",
			"path": "/",
			"sameSite": "no_restriction",
			"secure": true,
			"session": false,
			"storeId": "0",
			"value": "1.25"
		},
		{
			"domain": ".facebook.com",
			"expirationDate": 1674740989,
			"hostOnly": false,
			"httpOnly": false,
			"name": "wd",
			"path": "/",
			"sameSite": "lax",
			"secure": true,
			"session": false,
			"storeId": "0",
			"value": "1302x706"
		},
		{
			"domain": ".facebook.com",
			"expirationDate": 1705671507.604753,
			"hostOnly": false,
			"httpOnly": true,
			"name": "xs",
			"path": "/",
			"sameSite": "no_restriction",
			"secure": true,
			"session": false,
			"storeId": "0",
			"value": "1%3AkDWn0_RxsOWXRQ%3A2%3A1672060364%3A-1%3A6993%3A%3AAcUoMXyeYlG9VHUno1QFC93zWdUNmy2regy19I-YEFs"
		},
		{
			"domain": ".facebook.com",
			"expirationDate": 1681912073.543715,
			"hostOnly": false,
			"httpOnly": true,
			"name": "fr",
			"path": "/",
			"sameSite": "no_restriction",
			"secure": true,
			"session": false,
			"storeId": "0",
			"value": "0VTJOx3HoyqjnnNbZ.AWUITbic6T3p8--BAkvL8aPEIqI.BjyUfT.iW.AAA.0.0.BjyUoK.AWUdKJgT9bw"
		},
		{
			"domain": ".facebook.com",
			"hostOnly": false,
			"httpOnly": false,
			"name": "presence",
			"path": "/",
			"sameSite": "unspecified",
			"secure": true,
			"session": true,
			"storeId": "0",
			"value": "C%7B%22t3%22%3A%5B%5D%2C%22utc3%22%3A1674136185963%2C%22v%22%3A1%7D"
		}
	],
	"lastEventDate": "19.01.2023 13:55 petr d17",
	"email": "ovupexid1984@hotmail.com",
	"emailPassword": "oYiZjpOkDw",
	"imapHost": "outlook.office365.com",
	"imapPort": "993",
	"screenname": "Olya Girina",
	"birthdate": "1995 March 4",
	"country": "Kazakhstan",
	"isAvatarExists": false
}