{
	"sn": "facebook",
	"login": "100088852307074",
	"password": "qwe123rtY",
	"status": 2,
	"id": "100088852307074",
	"custom": {},
	"lastEventDate": "18.03.2023 06:01 petr d31",
	"name": "",
	"amountFriends": "97",
	"screenname": "Olga Snima",
	"birthdate": "1985 November 19",
	"country": "Kazakhstan",
	"isAvatarExists": false,
	"cookie": [
		{
			"domain": ".facebook.com",
			"expirationDate": 1707063028,
			"hostOnly": false,
			"httpOnly": true,
			"name": "sb",
			"path": "/",
			"sameSite": "no_restriction",
			"secure": true,
			"session": false,
			"storeId": "0",
			"value": "ooypY18Ji185ZZQCaapJQ2A4"
		},
		{
			"domain": ".facebook.com",
			"expirationDate": 1707063028,
			"hostOnly": false,
			"httpOnly": true,
			"name": "datr",
			"path": "/",
			"sameSite": "no_restriction",
			"secure": true,
			"session": false,
			"storeId": "0",
			"value": "ooypYyUaJkkrQN-VfS1kQla0"
		},
		{
			"domain": ".facebook.com",
			"expirationDate": 1710653771.572907,
			"hostOnly": false,
			"httpOnly": false,
			"name": "c_user",
			"path": "/",
			"sameSite": "no_restriction",
			"secure": true,
			"session": false,
			"storeId": "0",
			"value": "100088852307074"
		},
		{
			"domain": ".facebook.com",
			"expirationDate": 1679460780,
			"hostOnly": false,
			"httpOnly": false,
			"name": "dpr",
			"path": "/",
			"sameSite": "no_restriction",
			"secure": true,
			"session": false,
			"storeId": "0",
			"value": "1"
		},
		{
			"domain": ".facebook.com",
			"expirationDate": 1679723279,
			"hostOnly": false,
			"httpOnly": false,
			"name": "wd",
			"path": "/",
			"sameSite": "lax",
			"secure": true,
			"session": false,
			"storeId": "0",
			"value": "1300x704"
		},
		{
			"domain": ".facebook.com",
			"expirationDate": 1710653771.572995,
			"hostOnly": false,
			"httpOnly": true,
			"name": "xs",
			"path": "/",
			"sameSite": "no_restriction",
			"secure": true,
			"session": false,
			"storeId": "0",
			"value": "30%3AtGl_8Q3F74u6YA%3A2%3A1672056014%3A-1%3A7030%3A%3AAcWEFcauh1auYhnMz8LLX3tbyMW4CEJaA-FBdD6BhLU"
		},
		{
			"domain": ".facebook.com",
			"expirationDate": 1686894412.668161,
			"hostOnly": false,
			"httpOnly": true,
			"name": "fr",
			"path": "/",
			"sameSite": "no_restriction",
			"secure": true,
			"session": false,
			"storeId": "0",
			"value": "0o5xBVioDhlfwDgr3.AWUReBD1fMTnFWIgwRJjBQSo5tU.BkFU3M.B8.AAA.0.0.BkFVBN.AWXxRx6Yo-Y"
		},
		{
			"domain": ".facebook.com",
			"hostOnly": false,
			"httpOnly": false,
			"name": "usida",
			"path": "/",
			"sameSite": "no_restriction",
			"secure": true,
			"session": true,
			"storeId": "0",
			"value": "eyJ2ZXIiOjEsImlkIjoiQXJycGMxN2N4a2o4eiIsInRpbWUiOjE2NzkxMTg0MjB9"
		},
		{
			"domain": ".facebook.com",
			"hostOnly": false,
			"httpOnly": false,
			"name": "presence",
			"path": "/",
			"sameSite": "unspecified",
			"secure": true,
			"session": true,
			"storeId": "0",
			"value": "C%7B%22t3%22%3A%5B%5D%2C%22utc3%22%3A1679118476947%2C%22v%22%3A1%7D"
		}
	],
	"funPages": [
		"https://www.facebook.com/profile.php?id=100090198720138"
	]
}