{
	"sn": "facebook",
	"custom": {},
	"lastEventDate": "11.02.2023 18:02 petr d33",
	"status": 2,
	"id": "100087928284393",
	"name": "",
	"amountFriends": "192",
	"screenname": "Иоанна Соболева",
	"birthdate": "1997 November 27",
	"country": "",
	"isAvatarExists": false,
	"cookie": [
		{
			"domain": ".facebook.com",
			"expirationDate": 1707455083,
			"hostOnly": false,
			"httpOnly": true,
			"name": "datr",
			"path": "/",
			"sameSite": "no_restriction",
			"secure": true,
			"session": false,
			"storeId": "0",
			"value": "quLYYzGQ_rJbHZcvB87K5UFC"
		},
		{
			"domain": ".facebook.com",
			"expirationDate": 1707455083,
			"hostOnly": false,
			"httpOnly": true,
			"name": "sb",
			"path": "/",
			"sameSite": "no_restriction",
			"secure": true,
			"session": false,
			"storeId": "0",
			"value": "ruLYY7kRaEf-0_Y6WRQ5rFoA"
		},
		{
			"domain": ".facebook.com",
			"expirationDate": 1707673935.048086,
			"hostOnly": false,
			"httpOnly": false,
			"name": "c_user",
			"path": "/",
			"sameSite": "no_restriction",
			"secure": true,
			"session": false,
			"storeId": "0",
			"value": "100087928284393"
		},
		{
			"domain": ".facebook.com",
			"expirationDate": 1707455083,
			"hostOnly": false,
			"httpOnly": false,
			"name": "usida",
			"path": "/",
			"sameSite": "no_restriction",
			"secure": true,
			"session": false,
			"storeId": "0",
			"value": "eyJ2ZXIiOjEsImlkIjoiQXJwcG9xczFsb2hmYjAiLCJ0aW1lIjoxNjc1Nzc1NjIwfQ%3D%3D"
		},
		{
			"domain": ".facebook.com",
			"expirationDate": 1707673935.048182,
			"hostOnly": false,
			"httpOnly": true,
			"name": "xs",
			"path": "/",
			"sameSite": "no_restriction",
			"secure": true,
			"session": false,
			"storeId": "0",
			"value": "47%3ANp8oS488vXa1hQ%3A2%3A1675158224%3A-1%3A6993%3A%3AAcV1y36BYWVZF7pMMcgB2Fh9krPZw8vSL2ya9BzsBv8"
		},
		{
			"domain": ".facebook.com",
			"expirationDate": 1676742741,
			"hostOnly": false,
			"httpOnly": false,
			"name": "dpr",
			"path": "/",
			"sameSite": "no_restriction",
			"secure": true,
			"session": false,
			"storeId": "0",
			"value": "1"
		},
		{
			"domain": ".facebook.com",
			"expirationDate": 1676743187,
			"hostOnly": false,
			"httpOnly": false,
			"name": "wd",
			"path": "/",
			"sameSite": "lax",
			"secure": true,
			"session": false,
			"storeId": "0",
			"value": "1036x684"
		},
		{
			"domain": ".facebook.com",
			"expirationDate": 1683914261.921629,
			"hostOnly": false,
			"httpOnly": true,
			"name": "fr",
			"path": "/",
			"sameSite": "no_restriction",
			"secure": true,
			"session": false,
			"storeId": "0",
			"value": "0yxltvBB3QT9n00Rg.AWXL5BH7lvXKDdVyP8m2FQT7Trc.Bj59XP.-1.AAA.0.0.Bj59cW.AWV6vnFVG_g"
		},
		{
			"domain": ".facebook.com",
			"hostOnly": false,
			"httpOnly": false,
			"name": "presence",
			"path": "/",
			"sameSite": "unspecified",
			"secure": true,
			"session": true,
			"storeId": "0",
			"value": "C%7B%22lm3%22%3A%22u.100034319199658%22%2C%22t3%22%3A%5B%7B%22i%22%3A%22u.100070786367246%22%7D%2C%7B%22i%22%3A%22u.100086538871271%22%7D%5D%2C%22utc3%22%3A1676138361580%2C%22v%22%3A1%7D"
		}
	]
}