{
	"sn": "facebook",
	"status": 2,
	"id": "100087805677247",
	"name": "",
	"amountFriends": "",
	"screenname": "Джамиля Бирюкова",
	"birthdate": "1997 November 27",
	"country": "",
	"isAvatarExists": false,
	"cookie": [
		{
			"domain": ".facebook.com",
			"expirationDate": 1704787685.351648,
			"hostOnly": false,
			"httpOnly": true,
			"name": "sb",
			"path": "/",
			"sameSite": "no_restriction",
			"secure": true,
			"session": false,
			"storeId": "0",
			"value": "gP-FY-aJ8_0dlHByS5001GuV"
		},
		{
			"domain": ".facebook.com",
			"expirationDate": 1704787685.351813,
			"hostOnly": false,
			"httpOnly": true,
			"name": "datr",
			"path": "/",
			"sameSite": "no_restriction",
			"secure": true,
			"session": false,
			"storeId": "0",
			"value": "gP-FY9Tz7tD6Ol2mBzZVqbHN"
		},
		{
			"domain": ".facebook.com",
			"expirationDate": 1703086695.930025,
			"hostOnly": false,
			"httpOnly": false,
			"name": "c_user",
			"path": "/",
			"sameSite": "no_restriction",
			"secure": true,
			"session": false,
			"storeId": "0",
			"value": "100087805677247"
		},
		{
			"domain": ".facebook.com",
			"expirationDate": 1672155494,
			"hostOnly": false,
			"httpOnly": false,
			"name": "dpr",
			"path": "/",
			"sameSite": "no_restriction",
			"secure": true,
			"session": false,
			"storeId": "0",
			"value": "1"
		},
		{
			"domain": ".facebook.com",
			"expirationDate": 1672155792,
			"hostOnly": false,
			"httpOnly": false,
			"name": "wd",
			"path": "/",
			"sameSite": "lax",
			"secure": true,
			"session": false,
			"storeId": "0",
			"value": "1036x684"
		},
		{
			"domain": ".facebook.com",
			"expirationDate": 1703086695.930059,
			"hostOnly": false,
			"httpOnly": true,
			"name": "xs",
			"path": "/",
			"sameSite": "no_restriction",
			"secure": true,
			"session": false,
			"storeId": "0",
			"value": "47%3A1_ZYZr1rJ85LnA%3A2%3A1669726097%3A-1%3A-1%3A%3AAcX6gaSXYnU0KrdB9e0vV8KLvIZzjH7Hrqm_J7jRNUw"
		},
		{
			"domain": ".facebook.com",
			"expirationDate": 1679326836.868176,
			"hostOnly": false,
			"httpOnly": true,
			"name": "fr",
			"path": "/",
			"sameSite": "no_restriction",
			"secure": true,
			"session": false,
			"storeId": "0",
			"value": "0SScgvZeAYJewmjt1.AWWjIRBCaLBd5F7TOFri-7bA0jE.Bjodbo.z0.AAA.0.0.Bjodd1.AWWyoxvx1v8"
		},
		{
			"domain": ".facebook.com",
			"hostOnly": false,
			"httpOnly": false,
			"name": "presence",
			"path": "/",
			"sameSite": "unspecified",
			"secure": true,
			"session": true,
			"storeId": "0",
			"value": "C%7B%22t3%22%3A%5B%5D%2C%22utc3%22%3A1671550948813%2C%22v%22%3A1%7D"
		}
	],
	"lastEventDate": "20.12.2022 15:47 petr d16"
}