{
	"sn": "facebook",
	"custom": {},
	"lastEventDate": "22.02.2023 08:45 petr d32",
	"status": 2,
	"id": "100086871832962",
	"name": "",
	"amountFriends": "173",
	"screenname": "Shannon Stewart",
	"birthdate": "1995 December 22",
	"country": "Latvia",
	"isAvatarExists": false,
	"cookie": [
		{
			"domain": ".facebook.com",
			"expirationDate": 1707519925,
			"hostOnly": false,
			"httpOnly": true,
			"name": "datr",
			"path": "/",
			"sameSite": "no_restriction",
			"secure": true,
			"session": false,
			"storeId": "0",
			"value": "xtO-YzB_w7VCiFFiQVIVbWZz"
		},
		{
			"domain": ".facebook.com",
			"expirationDate": 1707519925,
			"hostOnly": false,
			"httpOnly": true,
			"name": "sb",
			"path": "/",
			"sameSite": "no_restriction",
			"secure": true,
			"session": false,
			"storeId": "0",
			"value": "ydO-Y5UhFCrRNYFVaK6W4WKE"
		},
		{
			"domain": ".facebook.com",
			"expirationDate": 1708520476.22106,
			"hostOnly": false,
			"httpOnly": false,
			"name": "c_user",
			"path": "/",
			"sameSite": "no_restriction",
			"secure": true,
			"session": false,
			"storeId": "0",
			"value": "100086871832962"
		},
		{
			"domain": ".facebook.com",
			"expirationDate": 1707519925,
			"hostOnly": false,
			"httpOnly": true,
			"name": "oo",
			"path": "/",
			"sameSite": "no_restriction",
			"secure": true,
			"session": false,
			"storeId": "0",
			"value": "v1"
		},
		{
			"domain": ".facebook.com",
			"expirationDate": 1677043340,
			"hostOnly": false,
			"httpOnly": false,
			"name": "cppo",
			"path": "/",
			"sameSite": "unspecified",
			"secure": true,
			"session": false,
			"storeId": "0",
			"value": "1"
		},
		{
			"domain": ".facebook.com",
			"hostOnly": false,
			"httpOnly": false,
			"name": "usida",
			"path": "/",
			"sameSite": "no_restriction",
			"secure": true,
			"session": true,
			"storeId": "0",
			"value": "eyJ2ZXIiOjEsImlkIjoiQXJxZjA5ODducHVjYiIsInRpbWUiOjE2NzY5NTY5NDB9"
		},
		{
			"domain": ".facebook.com",
			"expirationDate": 1677588964,
			"hostOnly": false,
			"httpOnly": false,
			"name": "dpr",
			"path": "/",
			"sameSite": "no_restriction",
			"secure": true,
			"session": false,
			"storeId": "0",
			"value": "1"
		},
		{
			"domain": ".facebook.com",
			"expirationDate": 1677589403,
			"hostOnly": false,
			"httpOnly": false,
			"name": "wd",
			"path": "/",
			"sameSite": "lax",
			"secure": true,
			"session": false,
			"storeId": "0",
			"value": "1036x684"
		},
		{
			"domain": ".facebook.com",
			"expirationDate": 1708520476.221114,
			"hostOnly": false,
			"httpOnly": true,
			"name": "xs",
			"path": "/",
			"sameSite": "no_restriction",
			"secure": true,
			"session": false,
			"storeId": "0",
			"value": "40%3A3DCU1l2eRP1rIw%3A2%3A1673450491%3A-1%3A3682%3A%3AAcUATGU8S2bfAQtzxwzk1lvhSP-4qx9eTT480DmYi7w"
		},
		{
			"domain": ".facebook.com",
			"expirationDate": 1684760502.951551,
			"hostOnly": false,
			"httpOnly": true,
			"name": "fr",
			"path": "/",
			"sameSite": "no_restriction",
			"secure": true,
			"session": false,
			"storeId": "0",
			"value": "08JgG03z9LPuSURTA.AWX8gJ_8X7vH1SliAczrczWRM_Q.Bj9MCd.Ma.AAA.0.0.Bj9MC3.AWXom5SgDYI"
		},
		{
			"domain": ".facebook.com",
			"hostOnly": false,
			"httpOnly": false,
			"name": "presence",
			"path": "/",
			"sameSite": "unspecified",
			"secure": true,
			"session": true,
			"storeId": "0",
			"value": "C%7B%22t3%22%3A%5B%7B%22i%22%3A%22u.100068108120729%22%7D%5D%2C%22utc3%22%3A1676984600268%2C%22v%22%3A1%7D"
		}
	],
	"funPages": [
		"https://www.facebook.com/Walk-tougether-111966535147277"
	]
}